{
  "date": "2026-04-02",
  "questions": [
    {
      "word": "Waarschuwing",
      "options": [
        "Verwittiging",
        "Gevaar",
        "Opletten",
        "Politie"
      ],
      "correctOption": "Gevaar"
    },
    {
      "word": "Koekjes",
      "options": [
        "Lekker",
        "Chocolade",
        "Eten",
        "Zoet"
      ],
      "correctOption": "Lekker"
    },
    {
      "word": "Commentaar",
      "options": [
        "Uitleg",
        "Kritiek",
        "Negatief",
        "Krant"
      ],
      "correctOption": "Kritiek"
    },
    {
      "word": "Klarinet",
      "options": [
        "Muziek",
        "Instrument",
        "Blazen",
        "Orkest"
      ],
      "correctOption": "Muziek"
    }
  ],
  "generatedAt": "2026-04-02T04:44:51.351Z"
}