{
  "date": "2026-03-30",
  "questions": [
    {
      "word": "Tram",
      "options": [
        "Spoor",
        "Trein",
        "Bus",
        "Stad"
      ],
      "correctOption": "Trein"
    },
    {
      "word": "Overste",
      "options": [
        "Baas",
        "Moeder",
        "Klooster",
        "Non"
      ],
      "correctOption": "Baas"
    },
    {
      "word": "Legaal",
      "options": [
        "Correct",
        "Wettelijk",
        "Wet",
        "Illegaal"
      ],
      "correctOption": "Wettelijk"
    },
    {
      "word": "Zuigen",
      "options": [
        "Borst",
        "Borstvoeding",
        "Baby",
        "Rietje"
      ],
      "correctOption": "Baby"
    }
  ],
  "generatedAt": "2026-03-30T20:21:26.529Z"
}